moz/l10n/__init__.py
moz/l10n/model.py
moz/l10n/py.typed
moz/l10n/bin/__init__.py
moz/l10n/bin/build.py
moz/l10n/bin/build_file.py
moz/l10n/bin/compare.py
moz/l10n/bin/fix.py
moz/l10n/bin/lint.py
moz/l10n/formats/__init__.py
moz/l10n/formats/android/__init__.py
moz/l10n/formats/android/parse.py
moz/l10n/formats/android/serialize.py
moz/l10n/formats/dtd/__init__.py
moz/l10n/formats/dtd/parse.py
moz/l10n/formats/dtd/serialize.py
moz/l10n/formats/fluent/__init__.py
moz/l10n/formats/fluent/parse.py
moz/l10n/formats/fluent/serialize.py
moz/l10n/formats/gettext/__init__.py
moz/l10n/formats/gettext/parse.py
moz/l10n/formats/gettext/serialize.py
moz/l10n/formats/inc/__init__.py
moz/l10n/formats/inc/parse.py
moz/l10n/formats/inc/serialize.py
moz/l10n/formats/ini/__init__.py
moz/l10n/formats/ini/parse.py
moz/l10n/formats/ini/serialize.py
moz/l10n/formats/mf2/__init__.py
moz/l10n/formats/mf2/from_json.py
moz/l10n/formats/mf2/message_parser.py
moz/l10n/formats/mf2/serialize.py
moz/l10n/formats/mf2/to_json.py
moz/l10n/formats/mf2/validate.py
moz/l10n/formats/plain_json/__init__.py
moz/l10n/formats/plain_json/parse.py
moz/l10n/formats/plain_json/serialize.py
moz/l10n/formats/properties/__init__.py
moz/l10n/formats/properties/parse.py
moz/l10n/formats/properties/serialize.py
moz/l10n/formats/webext/__init__.py
moz/l10n/formats/webext/parse.py
moz/l10n/formats/webext/serialize.py
moz/l10n/formats/xliff/__init__.py
moz/l10n/formats/xliff/common.py
moz/l10n/formats/xliff/parse.py
moz/l10n/formats/xliff/parse_trans_unit.py
moz/l10n/formats/xliff/parse_xcode.py
moz/l10n/formats/xliff/serialize.py
moz/l10n/formats/xliff/utils.py
moz/l10n/message/__init__.py
moz/l10n/message/from_json.py
moz/l10n/message/parse.py
moz/l10n/message/serialize.py
moz/l10n/message/to_json.py
moz/l10n/paths/__init__.py
moz/l10n/paths/android_locale.py
moz/l10n/paths/config.py
moz/l10n/paths/discover.py
moz/l10n/resource/__init__.py
moz/l10n/resource/add_entries.py
moz/l10n/resource/l10n_equal.py
moz_l10n-0.10.1.dist-info/METADATA
moz_l10n-0.10.1.dist-info/WHEEL
moz_l10n-0.10.1.dist-info/entry_points.txt
moz_l10n-0.10.1.dist-info/top_level.txt
moz_l10n-0.10.1.dist-info/RECORD
