Metadata-Version: 2.1
Name: moz.l10n
Version: 0.10.1
Summary: Mozilla tools for localization
Author-email: Mozilla <l10n-drivers@mozilla.org>, Eemeli Aro <eemeli@mozilla.com>
License: Apache-2.0
Project-URL: repository, https://github.com/mozilla/moz-l10n
Platform: any
Classifier: Development Status :: 4 - Beta
Classifier: Intended Audience :: Developers
Classifier: License :: OSI Approved :: Apache Software License
Classifier: Operating System :: OS Independent
Classifier: Programming Language :: Python
Classifier: Programming Language :: Python :: 3
Classifier: Programming Language :: Python :: 3.8
Classifier: Programming Language :: Python :: 3.9
Classifier: Programming Language :: Python :: 3.10
Classifier: Programming Language :: Python :: 3.11
Classifier: Programming Language :: Python :: 3.12
Classifier: Topic :: Software Development :: Libraries :: Python Modules
Classifier: Topic :: Software Development :: Localization
Classifier: Topic :: Software Development :: Testing
Requires-Python: ~=3.8
Requires-Dist: fluent.syntax ~=0.19.0
Requires-Dist: gitignorant ~=0.3.1
Requires-Dist: iniparse ~=0.5
Requires-Dist: polib ~=1.2
Requires-Dist: tomli >=1.1.0 ; python_version < "3.11"
Provides-Extra: xml
Requires-Dist: lxml <=5.4.0,>=5.0.0 ; extra == 'xml'
